[
	{
		"Наименование": "Абашев Руфат Амирович",
		"Ссылка": "Абашев Руфат Амирович",
		"Код": "000006146",
		"итого": "143456"
	},
	{
		"Наименование": "Або Владислав Арвельтович",
		"Ссылка": "Або Владислав Арвельтович",
		"Код": "000005925",
		"итого": "428345"
	},
	{
		"Наименование": "Абубакирова Нурия Рауфовна",
		"Ссылка": "Абубакирова Нурия Рауфовна",
		"Код": "000005132",
		"итого": "689219"
	},
	{
		"Наименование": "Авдонин Рифкат Юрьевич",
		"Ссылка": "Авдонин Рифкат Юрьевич",
		"Код": "000004319",
		"итого": "236101"
	},
	{
		"Наименование": "Агурьянов Юрий Николаевич",
		"Ссылка": "Агурьянов Юрий Николаевич",
		"Код": "000006408",
		"итого": "603709"
	},
	{
		"Наименование": "Азеев Айрат Фаридович",
		"Ссылка": "Азеев Айрат Фаридович",
		"Код": "000005974",
		"итого": "437144"
	},
	{
		"Наименование": "Александрова Ольга Юрьевна",
		"Ссылка": "Александрова Ольга Юрьевна",
		"Код": "000000001",
		"итого": "761853"
	},
	{
		"Наименование": "Алексеев Евгений Дмитриевич",
		"Ссылка": "Алексеев Евгений Дмитриевич",
		"Код": "000004848",
		"итого": "735202"
	},
	{
		"Наименование": "Амаков Никита Олегович",
		"Ссылка": "Амаков Никита Олегович",
		"Код": "000005821",
		"итого": "688147"
	},
	{
		"Наименование": "Антропова Людмила Александровна",
		"Ссылка": "Антропова Людмила Александровна",
		"Код": "000006280",
		"итого": "797245"
	},
	{
		"Наименование": "Ануфриева Екатерина Владимировна",
		"Ссылка": "Ануфриева Екатерина Владимировна",
		"Код": "000004603",
		"итого": "917289"
	},
	{
		"Наименование": "Арафайлова Екатерина Александровна",
		"Ссылка": "Арафайлова Екатерина Александровна",
		"Код": "000002605",
		"итого": "304383"
	},
	{
		"Наименование": "Асанди Евгений Сергеевич",
		"Ссылка": "Асанди Евгений Сергеевич",
		"Код": "000006013",
		"итого": "642220"
	},
	{
		"Наименование": "Асанова Анна Сергеевна",
		"Ссылка": "Асанова Анна Сергеевна",
		"Код": "000006104",
		"итого": "495458"
	},
	{
		"Наименование": "Бабушкин Сергей Константинович",
		"Ссылка": "Бабушкин Сергей Константинович",
		"Код": "000003024",
		"итого": "724679"
	},
	{
		"Наименование": "Бажанова Татьяна Владимировна",
		"Ссылка": "Бажанова Татьяна Владимировна",
		"Код": "000002986",
		"итого": "408644"
	},
	{
		"Наименование": "Баженова Мария Владимировна",
		"Ссылка": "Баженова Мария Владимировна",
		"Код": "000005181",
		"итого": "499183"
	},
	{
		"Наименование": "Банников Вадим Анатольевич",
		"Ссылка": "Банников Вадим Анатольевич",
		"Код": "000002654",
		"итого": "323756"
	},
	{
		"Наименование": "Банникова Наталья Валерьевна",
		"Ссылка": "Банникова Наталья Валерьевна",
		"Код": "000003617",
		"итого": "428249"
	},
	{
		"Наименование": "Баранов Александр Валентинович",
		"Ссылка": "Баранов Александр Валентинович",
		"Код": "000003800",
		"итого": "204849"
	},
	{
		"Наименование": "Баров Андрей Михайлович",
		"Ссылка": "Баров Андрей Михайлович",
		"Код": "000004262",
		"итого": "331732"
	},
	{
		"Наименование": "Бегишев Олег Николаевич",
		"Ссылка": "Бегишев Олег Николаевич",
		"Код": "000006002",
		"итого": "368903"
	},
	{
		"Наименование": "Безумов Александр Павлович",
		"Ссылка": "Безумов Александр Павлович",
		"Код": "000004666",
		"итого": "075750"
	},
	{
		"Наименование": "Березина Елена Геннадьевна",
		"Ссылка": "Березина Елена Геннадьевна",
		"Код": "000002454",
		"итого": "966872"
	},
	{
		"Наименование": "Беспалов Денис Павлович",
		"Ссылка": "Беспалов Денис Павлович",
		"Код": "000006412",
		"итого": "688635"
	},
	{
		"Наименование": "Благов Юрий Иванович",
		"Ссылка": "Благов Юрий Иванович",
		"Код": "000003060",
		"итого": "347894"
	},
	{
		"Наименование": "Близнюк Никита Григорьевич",
		"Ссылка": "Близнюк Никита Григорьевич",
		"Код": "000006388",
		"итого": "796545"
	},
	{
		"Наименование": "Богатырев Евгений Валерьевич",
		"Ссылка": "Богатырев Евгений Валерьевич",
		"Код": "000005950",
		"итого": "170519"
	},
	{
		"Наименование": "Богданов Владимир Алексеевич",
		"Ссылка": "Богданов Владимир Алексеевич",
		"Код": "000004246",
		"итого": "090002"
	},
	{
		"Наименование": "Богданов Константин Александрович",
		"Ссылка": "Богданов Константин Александрович",
		"Код": "000005990",
		"итого": "216708"
	},
	{
		"Наименование": "Богданова Наталья Михайловна",
		"Ссылка": "Богданова Наталья Михайловна",
		"Код": "000003500",
		"итого": "118409"
	},
	{
		"Наименование": "Большаков Никита Денисович",
		"Ссылка": "Большаков Никита Денисович",
		"Код": "000006439",
		"итого": "082473"
	},
	{
		"Наименование": "Бояршинов Антон Васильевич",
		"Ссылка": "Бояршинов Антон Васильевич",
		"Код": "000004962",
		"итого": "276559"
	},
	{
		"Наименование": "Бубра Галина Ивановна",
		"Ссылка": "Бубра Галина Ивановна",
		"Код": "000006422",
		"итого": "0622566"
	},
	{
		"Наименование": "Булаева Наталья Александровна",
		"Ссылка": "Булаева Наталья Александровна",
		"Код": "000004312",
		"итого": "596346"
	},
	{
		"Наименование": "Бусыгин Евгений Олегович",
		"Ссылка": "Бусыгин Евгений Олегович",
		"Код": "000006414",
		"итого": "488889"
	},
	{
		"Наименование": "Бутенко Роман Сергеевич",
		"Ссылка": "Бутенко Роман Сергеевич",
		"Код": "000002253",
		"итого": "461587"
	},
	{
		"Наименование": "Быкова Алина Алексеевна",
		"Ссылка": "Быкова Алина Алексеевна",
		"Код": "000006433",
		"итого": "826870"
	},
	{
		"Наименование": "Валиев Рустам Тимирзагитович",
		"Ссылка": "Валиев Рустам Тимирзагитович",
		"Код": "000006287",
		"итого": "923300"
	},
	{
		"Наименование": "Вальц Татьяна Александровна",
		"Ссылка": "Вальц Татьяна Александровна",
		"Код": "000006386",
		"итого": "964331"
	},
	{
		"Наименование": "Васильев Николай Валерьянович",
		"Ссылка": "Васильев Николай Валерьянович",
		"Код": "000003378",
		"итого": "861305"
	},
	{
		"Наименование": "Васильева Альфия Рафаиловна",
		"Ссылка": "Васильева Альфия Рафаиловна",
		"Код": "000003784",
		"итого": "743924"
	},
	{
		"Наименование": "Вершинина Алевтина Петровна",
		"Ссылка": "Вершинина Алевтина Петровна",
		"Код": "000006088",
		"итого": "242802"
	},
	{
		"Наименование": "Винжу Виктор Васильевич",
		"Ссылка": "Винжу Виктор Васильевич",
		"Код": "000006345",
		"итого": "913896"
	},
	{
		"Наименование": "Винников Андрей Геннадьевич",
		"Ссылка": "Винников Андрей Геннадьевич",
		"Код": "000005734",
		"итого": "140434"
	},
	{
		"Наименование": "Возженников Вячеслав Анатольевич",
		"Ссылка": "Возженников Вячеслав Анатольевич",
		"Код": "000002360",
		"итого": "818919"
	},
	{
		"Наименование": "Воробьева Елена Валерьевна",
		"Ссылка": "Воробьева Елена Валерьевна",
		"Код": "000004677",
		"итого": "574433"
	},
	{
		"Наименование": "Воронина Эльвира Равильевна",
		"Ссылка": "Воронина Эльвира Равильевна",
		"Код": "000006438",
		"итого": "974563"
	},
	{
		"Наименование": "Воронкова Елена Александровна",
		"Ссылка": "Воронкова Елена Александровна",
		"Код": "000006292",
		"итого": "768492"
	},
	{
		"Наименование": "Воронов Кирилл Сергеевич",
		"Ссылка": "Воронов Кирилл Сергеевич",
		"Код": "000005669",
		"итого": "312011"
	},
	{
		"Наименование": "Воронова Елена Владимировна",
		"Ссылка": "Воронова Елена Владимировна",
		"Код": "000005306",
		"итого": "073003"
	},
	{
		"Наименование": "Вшивков Виталий Александрович",
		"Ссылка": "Вшивков Виталий Александрович",
		"Код": "000004735",
		"итого": "425339"
	},
	{
		"Наименование": "Герасименко Игорь Леонидович",
		"Ссылка": "Герасименко Игорь Леонидович",
		"Код": "000006112",
		"итого": "367724"
	},
	{
		"Наименование": "Гимаева Ирина Зуфаровна",
		"Ссылка": "Гимаева Ирина Зуфаровна",
		"Код": "000005993",
		"итого": "197027"
	},
	{
		"Наименование": "Глухов Владимир Александрович",
		"Ссылка": "Глухов Владимир Александрович",
		"Код": "000004831",
		"итого": "371170"
	},
	{
		"Наименование": "Глухов Владислав Анатольевич",
		"Ссылка": "Глухов Владислав Анатольевич",
		"Код": "000005447",
		"итого": "723746"
	},
	{
		"Наименование": "Гоголева Ольга Анатольевна",
		"Ссылка": "Гоголева Ольга Анатольевна",
		"Код": "000003622",
		"итого": "241101"
	},
	{
		"Наименование": "Гогузева Татьяна Шайхинуровна",
		"Ссылка": "Гогузева Татьяна Шайхинуровна",
		"Код": "000006083",
		"итого": "247488"
	},
	{
		"Наименование": "Горбачев Евгений Владимирович",
		"Ссылка": "Горбачев Евгений Владимирович",
		"Код": "000003213",
		"итого": "692355"
	},
	{
		"Наименование": "Горбунов Павел Сергеевич",
		"Ссылка": "Горбунов Павел Сергеевич",
		"Код": "000006315",
		"итого": "951613"
	},
	{
		"Наименование": "Грачева Надежда Николаевна",
		"Ссылка": "Грачева Надежда Николаевна",
		"Код": "000000517",
		"итого": "896671"
	},
	{
		"Наименование": "Гречинский Дмитрий Владимирович",
		"Ссылка": "Гречинский Дмитрий Владимирович",
		"Код": "000004858",
		"итого": "320015"
	},
	{
		"Наименование": "Дегтярев Игорь Вячеславович",
		"Ссылка": "Дегтярев Игорь Вячеславович",
		"Код": "000006402",
		"итого": "530870"
	},
	{
		"Наименование": "Дедкова Марина Владимировна",
		"Ссылка": "Дедкова Марина Владимировна",
		"Код": "000006409",
		"итого": "920993"
	},
	{
		"Наименование": "Деньгин Сергей Геннадьевич",
		"Ссылка": "Деньгин Сергей Геннадьевич",
		"Код": "000004150",
		"итого": "590353"
	},
	{
		"Наименование": "Деревянко Евгения Владимировна",
		"Ссылка": "Деревянко Евгения Владимировна",
		"Код": "000006160",
		"итого": "079348"
	},
	{
		"Наименование": "Джаббаров Арзу Ильхам Оглы",
		"Ссылка": "Джаббаров Арзу Ильхам Оглы",
		"Код": "000005419",
		"итого": "289032"
	},
	{
		"Наименование": "Дресвянникова Светлана Рудольфовна",
		"Ссылка": "Дресвянникова Светлана Рудольфовна",
		"Код": "000000009",
		"итого": "995348"
	},
	{
		"Наименование": "Дуняшев Дамир Равильевич",
		"Ссылка": "Дуняшев Дамир Равильевич",
		"Код": "000006282",
		"итого": "253944"
	},
	{
		"Наименование": "Ежова Екатерина Федоровна",
		"Ссылка": "Ежова Екатерина Федоровна",
		"Код": "000003621",
		"итого": "147780"
	},
	{
		"Наименование": "Ершов Евгений Алексеевич",
		"Ссылка": "Ершов Евгений Алексеевич",
		"Код": "000005693",
		"итого": "663855"
	},
	{
		"Наименование": "Ефремов Федор Павлович",
		"Ссылка": "Ефремов Федор Павлович",
		"Код": "000003631",
		"итого": "505820"
	},
	{
		"Наименование": "Жигангиров Тимур Абузарович",
		"Ссылка": "Жигангиров Тимур Абузарович",
		"Код": "000006100",
		"итого": "067346"
	},
	{
		"Наименование": "Забавин Степан Владимирович",
		"Ссылка": "Забавин Степан Владимирович",
		"Код": "000006398",
		"итого": "342712"
	},
	{
		"Наименование": "Заберов Эдуард Федорович",
		"Ссылка": "Заберов Эдуард Федорович",
		"Код": "000006288",
		"итого": "746413"
	},
	{
		"Наименование": "Загребин Константин Владимирович",
		"Ссылка": "Загребин Константин Владимирович",
		"Код": "000005004",
		"итого": "440891"
	},
	{
		"Наименование": "Загуменнова  Анна Михайловна",
		"Ссылка": "Загуменнова  Анна Михайловна",
		"Код": "000003787",
		"итого": "372942"
	},
	{
		"Наименование": "Зайцев Михаил Васильевич",
		"Ссылка": "Зайцев Михаил Васильевич",
		"Код": "000006279",
		"итого": "593307"
	},
	{
		"Наименование": "Зарипов Рустам Ахметзянович",
		"Ссылка": "Зарипов Рустам Ахметзянович",
		"Код": "000000727",
		"итого": "476129"
	},
	{
		"Наименование": "Захваткин Виталий Владимирович",
		"Ссылка": "Захваткин Виталий Владимирович",
		"Код": "000006001",
		"итого": "236247"
	},
	{
		"Наименование": "Зверев Егор Алексеевич",
		"Ссылка": "Зверев Егор Алексеевич",
		"Код": "000006411",
		"итого": "858794"
	},
	{
		"Наименование": "Зотова Наталья Валерьевна",
		"Ссылка": "Зотова Наталья Валерьевна",
		"Код": "000004166",
		"итого": "841035"
	},
	{
		"Наименование": "Иванов Владимир Иванович",
		"Ссылка": "Иванов Владимир Иванович",
		"Код": "000005638",
		"итого": "994150"
	},
	{
		"Наименование": "Иванов Сергей Иванович",
		"Ссылка": "Иванов Сергей Иванович",
		"Код": "000005177",
		"итого": "208638"
	},
	{
		"Наименование": "Игнатьева Наталья Михайловна",
		"Ссылка": "Игнатьева Наталья Михайловна",
		"Код": "000004656",
		"итого": "494413"
	},
	{
		"Наименование": "Ижбулдин Тимур Раисович",
		"Ссылка": "Ижбулдин Тимур Раисович",
		"Код": "000006375",
		"итого": "023823"
	},
	{
		"Наименование": "Камаев Иван Юрьевич",
		"Ссылка": "Камаев Иван Юрьевич",
		"Код": "000004619",
		"итого": "093882"
	},
	{
		"Наименование": "Камашев Леонид Юрьевич",
		"Ссылка": "Камашев Леонид Юрьевич",
		"Код": "000006018",
		"итого": "867466"
	},
	{
		"Наименование": "Карабаев Владимир Семенович",
		"Ссылка": "Карабаев Владимир Семенович",
		"Код": "000006425",
		"итого": "956928"
	},
	{
		"Наименование": "Кашина Ольга Сергеевна",
		"Ссылка": "Кашина Ольга Сергеевна",
		"Код": "000004842",
		"итого": "801225"
	},
	{
		"Наименование": "Кашурникова Екатерина Леонтьевна",
		"Ссылка": "Кашурникова Екатерина Леонтьевна",
		"Код": "000005909",
		"итого": "156812"
	},
	{
		"Наименование": "Кириллова Марина Сергеевна",
		"Ссылка": "Кириллова Марина Сергеевна",
		"Код": "000000677",
		"итого": "970510"
	},
	{
		"Наименование": "Киселева Дарья Дмитриевна",
		"Ссылка": "Киселева Дарья Дмитриевна",
		"Код": "000006232",
		"итого": "441863"
	},
	{
		"Наименование": "Князева Татьяна Анатольевна",
		"Ссылка": "Князева Татьяна Анатольевна",
		"Код": "000003808",
		"итого": "957942"
	},
	{
		"Наименование": "Коваленко Оксана Александровна",
		"Ссылка": "Коваленко Оксана Александровна",
		"Код": "000005772",
		"итого": "033572"
	},
	{
		"Наименование": "Кокарева Анна Федоровна",
		"Ссылка": "Кокарева Анна Федоровна",
		"Код": "000006224",
		"итого": "361626"
	},
	{
		"Наименование": "Колеватова Оксана Васильевна",
		"Ссылка": "Колеватова Оксана Васильевна",
		"Код": "000006430",
		"итого": "966888"
	},
	{
		"Наименование": "Комов Иван Сергеевич",
		"Ссылка": "Комов Иван Сергеевич",
		"Код": "000002563",
		"итого": "540594"
	},
	{
		"Наименование": "Кондрашова Светлана Юрьевна",
		"Ссылка": "Кондрашова Светлана Юрьевна",
		"Код": "000004160",
		"итого": "616791"
	},
	{
		"Наименование": "Конев Павел Николаевич",
		"Ссылка": "Конев Павел Николаевич",
		"Код": "000006419",
		"итого": "903806"
	},
	{
		"Наименование": "Кононов Дмитрий Владимирович",
		"Ссылка": "Кононов Дмитрий Владимирович",
		"Код": "000003626",
		"итого": "617256"
	},
	{
		"Наименование": "Константинов Александр Александрович",
		"Ссылка": "Константинов Александр Александрович",
		"Код": "000004171",
		"итого": "398414"
	},
	{
		"Наименование": "Константинов Никита Юрьевич",
		"Ссылка": "Константинов Никита Юрьевич",
		"Код": "000006233",
		"итого": "091689"
	},
	{
		"Наименование": "Копысов Дмитрий Александрович",
		"Ссылка": "Копысов Дмитрий Александрович",
		"Код": "000004606",
		"итого": "992817"
	},
	{
		"Наименование": "Королев Дмитрий Анатольевич",
		"Ссылка": "Королев Дмитрий Анатольевич",
		"Код": "000002615",
		"итого": "483166"
	},
	{
		"Наименование": "Косовских Владимир Николаевич",
		"Ссылка": "Косовских Владимир Николаевич",
		"Код": "000006060",
		"итого": "586498"
	},
	{
		"Наименование": "Красноперов Евгений Николаевич",
		"Ссылка": "Красноперов Евгений Николаевич",
		"Код": "000005396",
		"итого": "049500"
	},
	{
		"Наименование": "Кропачев Алексей Владимирович",
		"Ссылка": "Кропачев Алексей Владимирович",
		"Код": "000002026",
		"итого": "965541"
	},
	{
		"Наименование": "Крылова Ольга Владимировна",
		"Ссылка": "Крылова Ольга Владимировна",
		"Код": "000003396",
		"итого": "613386"
	},
	{
		"Наименование": "Кудрявцев Владислав Владимирович",
		"Ссылка": "Кудрявцев Владислав Владимирович",
		"Код": "000006034",
		"итого": "617871"
	},
	{
		"Наименование": "Кузнецов Александр Сергеевич",
		"Ссылка": "Кузнецов Александр Сергеевич",
		"Код": "000006099",
		"итого": "112604"
	},
	{
		"Наименование": "Кузнецова Елена Анатольевна",
		"Ссылка": "Кузнецова Елена Анатольевна",
		"Код": "000002511",
		"итого": "744227"
	},
	{
		"Наименование": "Кулагина Татьяна Геннадьевна",
		"Ссылка": "Кулагина Татьяна Геннадьевна",
		"Код": "000004098",
		"итого": "288388"
	},
	{
		"Наименование": "Кулаков Сергей Александрович",
		"Ссылка": "Кулаков Сергей Александрович",
		"Код": "000000553",
		"итого": "180195"
	},
	{
		"Наименование": "Кулябин Алексей Владимирович",
		"Ссылка": "Кулябин Алексей Владимирович",
		"Код": "000006150",
		"итого": "139388"
	},
	{
		"Наименование": "Куракина Евгения Васильевна",
		"Ссылка": "Куракина Евгения Васильевна",
		"Код": "000004532",
		"итого": "796237"
	},
	{
		"Наименование": "Кутявин Иван Николаевич",
		"Ссылка": "Кутявин Иван Николаевич",
		"Код": "000006043",
		"итого": "537285"
	},
	{
		"Наименование": "Лаптева Ольга Викторовна",
		"Ссылка": "Лаптева Ольга Викторовна",
		"Код": "000006052",
		"итого": "735533"
	},
	{
		"Наименование": "Лапшин Игорь Игоревич",
		"Ссылка": "Лапшин Игорь Игоревич",
		"Код": "000006101",
		"итого": "025049"
	},
	{
		"Наименование": "Лекомцев Дмитрий Владимирович",
		"Ссылка": "Лекомцев Дмитрий Владимирович",
		"Код": "000006023",
		"итого": "495203"
	},
	{
		"Наименование": "Леонтьев Владимир Аркадьевич",
		"Ссылка": "Леонтьев Владимир Аркадьевич",
		"Код": "000000618",
		"итого": "494795"
	},
	{
		"Наименование": "Летута Александр Шарифович",
		"Ссылка": "Летута Александр Шарифович",
		"Код": "000005969",
		"итого": "749316"
	},
	{
		"Наименование": "Летута Сергей Александрович",
		"Ссылка": "Летута Сергей Александрович",
		"Код": "000003493",
		"итого": "711580"
	},
	{
		"Наименование": "Липовецкая Екатерина Ивановна",
		"Ссылка": "Липовецкая Екатерина Ивановна",
		"Код": "000006274",
		"итого": "028169"
	},
	{
		"Наименование": "Лихачев Андрей Александрович",
		"Ссылка": "Лихачев Андрей Александрович",
		"Код": "000005432",
		"итого": "581073"
	},
	{
		"Наименование": "Логинов Дмитрий Александрович",
		"Ссылка": "Логинов Дмитрий Александрович",
		"Код": "000000630",
		"итого": "764464"
	},
	{
		"Наименование": "Ложкин Михаил Владимирович",
		"Ссылка": "Ложкин Михаил Владимирович",
		"Код": "000002514",
		"итого": "145944"
	},
	{
		"Наименование": "Ломаева Елена Борисовна",
		"Ссылка": "Ломаева Елена Борисовна",
		"Код": "000002406",
		"итого": "827031"
	},
	{
		"Наименование": "Лукина Мария Викторовна",
		"Ссылка": "Лукина Мария Викторовна",
		"Код": "000003956",
		"итого": "144834"
	},
	{
		"Наименование": "Лямина Татьяна Леонидовна",
		"Ссылка": "Лямина Татьяна Леонидовна",
		"Код": "000003373",
		"итого": "699063"
	},
	{
		"Наименование": "Мальгинов Роман Юрьевич",
		"Ссылка": "Мальгинов Роман Юрьевич",
		"Код": "000006397",
		"итого": "248243"
	},
	{
		"Наименование": "Мамонтов Константин Михайлович",
		"Ссылка": "Мамонтов Константин Михайлович",
		"Код": "000006077",
		"итого": "811121"
	},
	{
		"Наименование": "Мачок Владимир Петрович",
		"Ссылка": "Мачок Владимир Петрович",
		"Код": "000006390",
		"итого": "491419"
	},
	{
		"Наименование": "Машарипов Андрей Николаевич",
		"Ссылка": "Машарипов Андрей Николаевич",
		"Код": "000005988",
		"итого": "801101"
	},
	{
		"Наименование": "Меньшиков Сергей Викторович",
		"Ссылка": "Меньшиков Сергей Викторович",
		"Код": "000005234",
		"итого": "541624"
	},
	{
		"Наименование": "Меньшикова Ольга Владимировна",
		"Ссылка": "Меньшикова Ольга Владимировна",
		"Код": "000005010",
		"итого": "944887"
	},
	{
		"Наименование": "Миронова Валентина Викторовна",
		"Ссылка": "Миронова Валентина Викторовна",
		"Код": "000006200",
		"итого": "897321"
	},
	{
		"Наименование": "Мирошниченко Денис Николаевич",
		"Ссылка": "Мирошниченко Денис Николаевич",
		"Код": "000005038",
		"итого": "148324"
	},
	{
		"Наименование": "Михайлов Петр Иванович",
		"Ссылка": "Михайлов Петр Иванович",
		"Код": "000002407",
		"итого": "045450"
	},
	{
		"Наименование": "Михайлова Алёна Николаевна",
		"Ссылка": "Михайлова Алёна Николаевна",
		"Код": "000002955",
		"итого": "896988"
	},
	{
		"Наименование": "Михайлюк Юрий Федорович",
		"Ссылка": "Михайлюк Юрий Федорович",
		"Код": "000005583",
		"итого": "353325"
	},
	{
		"Наименование": "Михеев Владимир Викторович",
		"Ссылка": "Михеев Владимир Викторович",
		"Код": "000005609",
		"итого": "942209"
	},
	{
		"Наименование": "Мокин Леонид Кронитович",
		"Ссылка": "Мокин Леонид Кронитович",
		"Код": "000000147",
		"итого": "692738"
	},
	{
		"Наименование": "Мороз Тамара Сергеевна",
		"Ссылка": "Мороз Тамара Сергеевна",
		"Код": "000005197",
		"итого": "312057"
	},
	{
		"Наименование": "Мохначев Алексей Михайлович",
		"Ссылка": "Мохначев Алексей Михайлович",
		"Код": "000002457",
		"итого": "422004"
	},
	{
		"Наименование": "Мохначева Екатерина Анатольевна",
		"Ссылка": "Мохначева Екатерина Анатольевна",
		"Код": "000003169",
		"итого": "264877"
	},
	{
		"Наименование": "Мощевитина Валерия Александровна",
		"Ссылка": "Мощевитина Валерия Александровна",
		"Код": "000002691",
		"итого": "716095"
	},
	{
		"Наименование": "Муртазина Альбина Эдвардовна",
		"Ссылка": "Муртазина Альбина Эдвардовна",
		"Код": "000004870",
		"итого": "737923"
	},
	{
		"Наименование": "Набиев Марат Ринатович",
		"Ссылка": "Набиев Марат Ринатович",
		"Код": "000006208",
		"итого": "043437"
	},
	{
		"Наименование": "Наговицын Андрей Владимирович",
		"Ссылка": "Наговицын Андрей Владимирович",
		"Код": "000002521",
		"итого": "861281"
	},
	{
		"Наименование": "Наговицына Елена Вячеславовна",
		"Ссылка": "Наговицына Елена Вячеславовна",
		"Код": "000002900",
		"итого": "374312"
	},
	{
		"Наименование": "Назаров Руслан Владимирович",
		"Ссылка": "Назаров Руслан Владимирович",
		"Код": "000003551",
		"итого": "548454"
	},
	{
		"Наименование": "Ненахова Анна Демидовна",
		"Ссылка": "Ненахова Анна Демидовна",
		"Код": "000006355",
		"итого": "680149"
	},
	{
		"Наименование": "Низамбеева Ольга Валерьевна",
		"Ссылка": "Низамбеева Ольга Валерьевна",
		"Код": "000004739",
		"итого": "043033"
	},
	{
		"Наименование": "Низамутдинов Ильнас Рамилевич",
		"Ссылка": "Низамутдинов Ильнас Рамилевич",
		"Код": "000006164",
		"итого": "827172"
	},
	{
		"Наименование": "Николаев Сергей Андреевич",
		"Ссылка": "Николаев Сергей Андреевич",
		"Код": "000000632",
		"итого": "739075"
	},
	{
		"Наименование": "Ноянова Оксана Александровна",
		"Ссылка": "Ноянова Оксана Александровна",
		"Код": "000000662",
		"итого": "844474"
	},
	{
		"Наименование": "Нукин Даулет Жакслыкович",
		"Ссылка": "Нукин Даулет Жакслыкович",
		"Код": "000006410",
		"итого": "526329"
	},
	{
		"Наименование": "Оборина Анастасия Михайловна",
		"Ссылка": "Оборина Анастасия Михайловна",
		"Код": "000003023",
		"итого": "894188"
	},
	{
		"Наименование": "Одинцова Мария Сергеевна",
		"Ссылка": "Одинцова Мария Сергеевна",
		"Код": "000004123",
		"итого": "594842"
	},
	{
		"Наименование": "Павлов Сергей Аркадьевич",
		"Ссылка": "Павлов Сергей Аркадьевич",
		"Код": "000003728",
		"итого": "865407"
	},
	{
		"Наименование": "Панаскина Наталья Николаевна",
		"Ссылка": "Панаскина Наталья Николаевна",
		"Код": "000000053",
		"итого": "492053"
	},
	{
		"Наименование": "Панфилов Сергей Семенович",
		"Ссылка": "Панфилов Сергей Семенович",
		"Код": "000004180",
		"итого": "426727"
	},
	{
		"Наименование": "Пастушкова Альбина Ерджаниковна",
		"Ссылка": "Пастушкова Альбина Ерджаниковна",
		"Код": "000005750",
		"итого": "663660"
	},
	{
		"Наименование": "Пепеляев Евгений Геннадиевич",
		"Ссылка": "Пепеляев Евгений Геннадиевич",
		"Код": "000006199",
		"итого": "391180"
	},
	{
		"Наименование": "Перевалов Валерий Александрович",
		"Ссылка": "Перевалов Валерий Александрович",
		"Код": "000005050",
		"итого": "727657"
	},
	{
		"Наименование": "Перевощиков Дмитрий Владимирович",
		"Ссылка": "Перевощиков Дмитрий Владимирович",
		"Код": "000004727",
		"итого": "547083"
	},
	{
		"Наименование": "Перминов Данил Игоревич",
		"Ссылка": "Перминов Данил Игоревич",
		"Код": "000005793",
		"итого": "492515"
	},
	{
		"Наименование": "Перышкин Виктор Борисович",
		"Ссылка": "Перышкин Виктор Борисович",
		"Код": "000004177",
		"итого": "358709"
	},
	{
		"Наименование": "Петерс Александр Викторович",
		"Ссылка": "Петерс Александр Викторович",
		"Код": "000005819",
		"итого": "295823"
	},
	{
		"Наименование": "Петков Иван Алексеевич",
		"Ссылка": "Петков Иван Алексеевич",
		"Код": "000005835",
		"итого": "686436"
	},
	{
		"Наименование": "Петухов Сергей Валерьевич",
		"Ссылка": "Петухов Сергей Валерьевич",
		"Код": "000006038",
		"итого": "347545"
	},
	{
		"Наименование": "Поздеев Сергей Евгеньевич",
		"Ссылка": "Поздеев Сергей Евгеньевич",
		"Код": "000005075",
		"итого": "446416"
	},
	{
		"Наименование": "Пойлов Александр Владимирович",
		"Ссылка": "Пойлов Александр Владимирович",
		"Код": "000000683",
		"итого": "937966"
	},
	{
		"Наименование": "Покачалов Евгений Андреевич",
		"Ссылка": "Покачалов Евгений Андреевич",
		"Код": "000005424",
		"итого": "288673"
	},
	{
		"Наименование": "Пономарев Василий Алексеевич",
		"Ссылка": "Пономарев Василий Алексеевич",
		"Код": "000006379",
		"итого": "657898"
	},
	{
		"Наименование": "Пономарев Виктор Инокентьевич",
		"Ссылка": "Пономарев Виктор Инокентьевич",
		"Код": "000004496",
		"итого": "514801"
	},
	{
		"Наименование": "Попов Алексей Анатольевич",
		"Ссылка": "Попов Алексей Анатольевич",
		"Код": "000006227",
		"итого": "609230"
	},
	{
		"Наименование": "Постников Алексей Вячеславович",
		"Ссылка": "Постников Алексей Вячеславович",
		"Код": "000006096",
		"итого": "512214"
	},
	{
		"Наименование": "Потапов Павел Андреевич",
		"Ссылка": "Потапов Павел Андреевич",
		"Код": "000002113",
		"итого": "627175"
	},
	{
		"Наименование": "Прозоров Игорь Станиславович",
		"Ссылка": "Прозоров Игорь Станиславович",
		"Код": "000004903",
		"итого": "801348"
	},
	{
		"Наименование": "Пушин Дмитрий Александрович",
		"Ссылка": "Пушин Дмитрий Александрович",
		"Код": "000006346",
		"итого": "116335"
	},
	{
		"Наименование": "Пушкарев Марат Владимирович",
		"Ссылка": "Пушкарев Марат Владимирович",
		"Код": "000005751",
		"итого": "348737"
	},
	{
		"Наименование": "Пушкарев Михаил Георгиевич",
		"Ссылка": "Пушкарев Михаил Георгиевич",
		"Код": "000000483",
		"итого": "370276"
	},
	{
		"Наименование": "Ральников Антон Васильевич",
		"Ссылка": "Ральников Антон Васильевич",
		"Код": "000006320",
		"итого": "680359"
	},
	{
		"Наименование": "Рубанова Александра Евгеньевна",
		"Ссылка": "Рубанова Александра Евгеньевна",
		"Код": "000005911",
		"итого": "970325"
	},
	{
		"Наименование": "Рудин Антон Дмитриевич",
		"Ссылка": "Рудин Антон Дмитриевич",
		"Код": "000006148",
		"итого": "736060"
	},
	{
		"Наименование": "Рудой Владимир Михайлович",
		"Ссылка": "Рудой Владимир Михайлович",
		"Код": "000005589",
		"итого": "972316"
	},
	{
		"Наименование": "Русинова Наталья Анатольевна",
		"Ссылка": "Русинова Наталья Анатольевна",
		"Код": "000006368",
		"итого": "507271"
	},
	{
		"Наименование": "Рябина Екатерина Сергеевна",
		"Ссылка": "Рябина Екатерина Сергеевна",
		"Код": "000004219",
		"итого": "813899"
	},
	{
		"Наименование": "Сабуров Юрий Николаевич",
		"Ссылка": "Сабуров Юрий Николаевич",
		"Код": "000006111",
		"итого": "847397"
	},
	{
		"Наименование": "Савельева Ольга Игоревна",
		"Ссылка": "Савельева Ольга Игоревна",
		"Код": "000004701",
		"итого": "689678"
	},
	{
		"Наименование": "Садыков Марсель Фагатович",
		"Ссылка": "Садыков Марсель Фагатович",
		"Код": "000006362",
		"итого": "089740"
	},
	{
		"Наименование": "Салюк Глеб Александрович",
		"Ссылка": "Салюк Глеб Александрович",
		"Код": "000003667",
		"итого": "218194"
	},
	{
		"Наименование": "Самохин Александр Юрьевич",
		"Ссылка": "Самохин Александр Юрьевич",
		"Код": "000006039",
		"итого": "807042"
	},
	{
		"Наименование": "Сафиуллин Александр Альбертович",
		"Ссылка": "Сафиуллин Александр Альбертович",
		"Код": "000005719",
		"итого": "095929"
	},
	{
		"Наименование": "Семенов Константин Юрьевич",
		"Ссылка": "Семенов Константин Юрьевич",
		"Код": "000006225",
		"итого": "677460"
	},
	{
		"Наименование": "Семина Наталья Александровна",
		"Ссылка": "Семина Наталья Александровна",
		"Код": "000006318",
		"итого": "293848"
	},
	{
		"Наименование": "Середов Сергей Михайлович",
		"Ссылка": "Середов Сергей Михайлович",
		"Код": "000000156",
		"итого": "985299"
	},
	{
		"Наименование": "Сесюнина Елизавета Алексеевна",
		"Ссылка": "Сесюнина Елизавета Алексеевна",
		"Код": "000002250",
		"итого": "611568"
	},
	{
		"Наименование": "Сизиков Сергей Анатольевич",
		"Ссылка": "Сизиков Сергей Анатольевич",
		"Код": "000006258",
		"итого": "929662"
	},
	{
		"Наименование": "Симанов Дмитрий Зоранович",
		"Ссылка": "Симанов Дмитрий Зоранович",
		"Код": "000005754",
		"итого": "269338"
	},
	{
		"Наименование": "Симушкин Сергей Альбертович",
		"Ссылка": "Симушкин Сергей Альбертович",
		"Код": "000006421",
		"итого": "646032"
	},
	{
		"Наименование": "Скорникова Марина Владимировна",
		"Ссылка": "Скорникова Марина Владимировна",
		"Код": "000006271",
		"итого": "205800"
	},
	{
		"Наименование": "Соболева Ульяна Леонидовна",
		"Ссылка": "Соболева Ульяна Леонидовна",
		"Код": "000005210",
		"итого": "408887"
	},
	{
		"Наименование": "Соломенников Максим Сергеевич",
		"Ссылка": "Соломенников Максим Сергеевич",
		"Код": "000004715",
		"итого": "817310"
	},
	{
		"Наименование": "Ставицкая Татьяна Сергеевна",
		"Ссылка": "Ставицкая Татьяна Сергеевна",
		"Код": "000006201",
		"итого": "309939"
	},
	{
		"Наименование": "Степанов Павел Васильевич",
		"Ссылка": "Степанов Павел Васильевич",
		"Код": "000004729",
		"итого": "823640"
	},
	{
		"Наименование": "Стерхов Алексей Николаевич",
		"Ссылка": "Стерхов Алексей Николаевич",
		"Код": "000002470",
		"итого": "887621"
	},
	{
		"Наименование": "Стрелков Дмитрий Анатольевич",
		"Ссылка": "Стрелков Дмитрий Анатольевич",
		"Код": "000006257",
		"итого": "747912"
	},
	{
		"Наименование": "Стрелкова Татьяна Петровна",
		"Ссылка": "Стрелкова Татьяна Петровна",
		"Код": "000005947",
		"итого": "817901"
	},
	{
		"Наименование": "Стрижов Николай Борисович",
		"Ссылка": "Стрижов Николай Борисович",
		"Код": "000002530",
		"итого": "981579"
	},
	{
		"Наименование": "Суворова Елена Сергеевна",
		"Ссылка": "Суворова Елена Сергеевна",
		"Код": "000003341",
		"итого": "125023"
	},
	{
		"Наименование": "Таган Лилия Владимировна",
		"Ссылка": "Таган Лилия Владимировна",
		"Код": "000006373",
		"итого": "107691"
	},
	{
		"Наименование": "Ташкинова Ирина Вадимовна",
		"Ссылка": "Ташкинова Ирина Вадимовна",
		"Код": "000003798",
		"итого": "643832"
	},
	{
		"Наименование": "Терехов Сергей Витальевич",
		"Ссылка": "Терехов Сергей Витальевич",
		"Код": "000006395",
		"итого": "588937"
	},
	{
		"Наименование": "Тимергалин Марат Рамилевич",
		"Ссылка": "Тимергалин Марат Рамилевич",
		"Код": "000004475",
		"итого": "604256"
	},
	{
		"Наименование": "Тимофеев Никита Алексеевич",
		"Ссылка": "Тимофеев Никита Алексеевич",
		"Код": "000006203",
		"итого": "972944"
	},
	{
		"Наименование": "Троегубов Тимур Николаевич",
		"Ссылка": "Троегубов Тимур Николаевич",
		"Код": "000002708",
		"итого": "539379"
	},
	{
		"Наименование": "Тронин Василий Михайлович",
		"Ссылка": "Тронин Василий Михайлович",
		"Код": "000006084",
		"итого": "316516"
	},
	{
		"Наименование": "Трубицына Елизавета Викторовна",
		"Ссылка": "Трубицына Елизавета Викторовна",
		"Код": "000005539",
		"итого": "156985"
	},
	{
		"Наименование": "Тугашев Андрей Георгиевич",
		"Ссылка": "Тугашев Андрей Георгиевич",
		"Код": "000006428",
		"итого": "579009"
	},
	{
		"Наименование": "Тупицын Андрей Валентинович",
		"Ссылка": "Тупицын Андрей Валентинович",
		"Код": "000006339",
		"итого": "081906"
	},
	{
		"Наименование": "Тютнев Олег Александрович",
		"Ссылка": "Тютнев Олег Александрович",
		"Код": "000004967",
		"итого": "205684"
	},
	{
		"Наименование": "Урсегов Лев Михайлович",
		"Ссылка": "Урсегов Лев Михайлович",
		"Код": "000004163",
		"итого": "840955"
	},
	{
		"Наименование": "Урсегова Ирина Витальевна",
		"Ссылка": "Урсегова Ирина Витальевна",
		"Код": "000002940",
		"итого": "337602"
	},
	{
		"Наименование": "Усенко Алексей Геннадьевич",
		"Ссылка": "Усенко Алексей Геннадьевич",
		"Код": "000004871",
		"итого": "515556"
	},
	{
		"Наименование": "Фаткуллин Вильян Валериянович",
		"Ссылка": "Фаткуллин Вильян Валериянович",
		"Код": "000005065",
		"итого": "494566"
	},
	{
		"Наименование": "Фахрутдинов Дамир Анварович",
		"Ссылка": "Фахрутдинов Дамир Анварович",
		"Код": "000006304",
		"итого": "875594"
	},
	{
		"Наименование": "Фахрутдинов Ильшат Ильдарович",
		"Ссылка": "Фахрутдинов Ильшат Ильдарович",
		"Код": "000006234",
		"итого": "263586"
	},
	{
		"Наименование": "Федорова Елена Петровна",
		"Ссылка": "Федорова Елена Петровна",
		"Код": "000003980",
		"итого": "145821"
	},
	{
		"Наименование": "Фомина Виктория Игоревна",
		"Ссылка": "Фомина Виктория Игоревна",
		"Код": "000005327",
		"итого": "449513"
	},
	{
		"Наименование": "Форостенко Наталья Викторовна",
		"Ссылка": "Форостенко Наталья Викторовна",
		"Код": "000003449",
		"итого": "515843"
	},
	{
		"Наименование": "Фот Татьяна Сергеевна",
		"Ссылка": "Фот Татьяна Сергеевна",
		"Код": "000005426",
		"итого": "438655"
	},
	{
		"Наименование": "Хаврюченко Александр Николаевич",
		"Ссылка": "Хаврюченко Александр Николаевич",
		"Код": "000003718",
		"итого": "390790"
	},
	{
		"Наименование": "Халиуллин Руслан Дамирович",
		"Ссылка": "Халиуллин Руслан Дамирович",
		"Код": "000006024",
		"итого": "362195"
	},
	{
		"Наименование": "Хитрин Дмитрий Александрович",
		"Ссылка": "Хитрин Дмитрий Александрович",
		"Код": "000004441",
		"итого": "579231"
	},
	{
		"Наименование": "Хомякова Елена Витальевна",
		"Ссылка": "Хомякова Елена Витальевна",
		"Код": "000006244",
		"итого": "266017"
	},
	{
		"Наименование": "Хузягаллеев Тимур Русланович",
		"Ссылка": "Хузягаллеев Тимур Русланович",
		"Код": "000005951",
		"итого": "554368"
	},
	{
		"Наименование": "Цылев Антон Валерьевич",
		"Ссылка": "Цылев Антон Валерьевич",
		"Код": "000006432",
		"итого": "841711"
	},
	{
		"Наименование": "Чайникова Снежана Геннадьевна",
		"Ссылка": "Чайникова Снежана Геннадьевна",
		"Код": "000004909",
		"итого": "892345"
	},
	{
		"Наименование": "Червяков Константин Александрович",
		"Ссылка": "Червяков Константин Александрович",
		"Код": "000006086",
		"итого": "401350"
	},
	{
		"Наименование": "Черных Наталья Владимировна",
		"Ссылка": "Черных Наталья Владимировна",
		"Код": "000005815",
		"итого": "897635"
	},
	{
		"Наименование": "Чиркова Анна Анатольевна",
		"Ссылка": "Чиркова Анна Анатольевна",
		"Код": "000006004",
		"итого": "812913"
	},
	{
		"Наименование": "Чубуков Денис Сергеевич",
		"Ссылка": "Чубуков Денис Сергеевич",
		"Код": "000004763",
		"итого": "690442"
	},
	{
		"Наименование": "Чувашева Татьяна Геннадьевна",
		"Ссылка": "Чувашева Татьяна Геннадьевна",
		"Код": "000006246",
		"итого": "162263"
	},
	{
		"Наименование": "Чуркин Алексей Вячеславович",
		"Ссылка": "Чуркин Алексей Вячеславович",
		"Код": "000002856",
		"итого": "307033"
	},
	{
		"Наименование": "Чухланцев Алексей Николаевич",
		"Ссылка": "Чухланцев Алексей Николаевич",
		"Код": "000000036",
		"итого": "230518"
	},
	{
		"Наименование": "Чухланцева Светлана Викторовна",
		"Ссылка": "Чухланцева Светлана Викторовна",
		"Код": "000002080",
		"итого": "432719"
	},
	{
		"Наименование": "Шабалин Тарас Владимирович",
		"Ссылка": "Шабалин Тарас Владимирович",
		"Код": "000005978",
		"итого": "743134"
	},
	{
		"Наименование": "Шаймарданов Альберт Баграмович",
		"Ссылка": "Шаймарданов Альберт Баграмович",
		"Код": "000004652",
		"итого": "970789"
	},
	{
		"Наименование": "Шаромов Дмитрий Юрьевич",
		"Ссылка": "Шаромов Дмитрий Юрьевич",
		"Код": "000005591",
		"итого": "373341"
	},
	{
		"Наименование": "Шахматова Ольга Валерьевна",
		"Ссылка": "Шахматова Ольга Валерьевна",
		"Код": "000005442",
		"итого": "162652"
	},
	{
		"Наименование": "Шеин Николай Владимирович",
		"Ссылка": "Шеин Николай Владимирович",
		"Код": "000006098",
		"итого": "189677"
	},
	{
		"Наименование": "Шерстобитова Ирина Николаевна",
		"Ссылка": "Шерстобитова Ирина Николаевна",
		"Код": "000005617",
		"итого": "793859"
	},
	{
		"Наименование": "Шибанова Марина Владимировна",
		"Ссылка": "Шибанова Марина Владимировна",
		"Код": "000000185",
		"итого": "687890"
	},
	{
		"Наименование": "Шипунова Юлия Владимировна",
		"Ссылка": "Шипунова Юлия Владимировна",
		"Код": "000005959",
		"итого": "435902"
	},
	{
		"Наименование": "Широбоков Михаил Александрович",
		"Ссылка": "Широбоков Михаил Александрович",
		"Код": "000006434",
		"итого": "919137"
	},
	{
		"Наименование": "Широбокова Надежда Анатольевна",
		"Ссылка": "Широбокова Надежда Анатольевна",
		"Код": "000003259",
		"итого": "614471"
	},
	{
		"Наименование": "Шишкина Ирина Владимировна",
		"Ссылка": "Шишкина Ирина Владимировна",
		"Код": "000005791",
		"итого": "046989"
	},
	{
		"Наименование": "Щанкина Анна Константиновна",
		"Ссылка": "Щанкина Анна Константиновна",
		"Код": "000006144",
		"итого": "270439"
	},
	{
		"Наименование": "Щанова Елена Анатольевна",
		"Ссылка": "Щанова Елена Анатольевна",
		"Код": "000000654",
		"итого": "028846"
	},
	{
		"Наименование": "Эсенбаев Вадим Валерьевич",
		"Ссылка": "Эсенбаев Вадим Валерьевич",
		"Код": "000004151",
		"итого": "070454"
	},
	{
		"Наименование": "Юнусов Ильгиз Маратович",
		"Ссылка": "Юнусов Ильгиз Маратович",
		"Код": "000004224",
		"итого": "069822"
	},
	{
		"Наименование": "Юрлова Анна Владимировна",
		"Ссылка": "Юрлова Анна Владимировна",
		"Код": "000004016",
		"итого": "933716"
	},
	{
		"Наименование": "Юрченко Екатерина Андреевна",
		"Ссылка": "Юрченко Екатерина Андреевна",
		"Код": "000004610",
		"итого": "646498"
	},
	{
		"Наименование": "Якимовских Дмитрий Сергеевич",
		"Ссылка": "Якимовских Дмитрий Сергеевич",
		"Код": "000005985",
		"итого": "185152"
	},
	{
		"Наименование": "Яковлев Олег Викторович",
		"Ссылка": "Яковлев Олег Викторович",
		"Код": "000003599",
		"итого": "395039"
	},
	{
		"Наименование": "Яковлева Елена Владимировна",
		"Ссылка": "Яковлева Елена Владимировна",
		"Код": "000004138",
		"итого": "569437"
	},
	{
		"Наименование": "Якубов Александр Александрович",
		"Ссылка": "Якубов Александр Александрович",
		"Код": "000002092",
		"итого": "594931"
	},
	{
		"Наименование": "Якубов Алексей Александрович",
		"Ссылка": "Якубов Алексей Александрович",
		"Код": "000002133",
		"итого": "627206"
	},
	{
		"Наименование": "Якубов Павел Александрович",
		"Ссылка": "Якубов Павел Александрович",
		"Код": "000003191",
		"итого": "994151"
	},
	{
		"Наименование": "Ямшанов Иван Алексеевич",
		"Ссылка": "Ямшанов Иван Алексеевич",
		"Код": "000006155",
		"итого": "248828"
	}
]